{
	"title": "Recrea't",
	"titleTemplate": "%s · Recrea't",
	"description": "Disseny gràfic i comunicació",
	"siteUrl": "https://recreat.cat",
	"image": "/images/Logo.svg",
	"color": "#E8864B",
	"author": {
		"name": "Recrea't",
		"url": "https://recreat.cat"
	},
	"organization": {
		"name": "Recrea't",
		"url": "https://recreat.cat",
		"logo": "/images/icon.png",
		"email": "recreat.info@gmail.com",
		"phone": {
			"number": 34646429298,
			"title": "646 429 298"
		},
		"address": "Carrer Major XX<br/>1a planta</br>25580 Esterri d'Àneu"
	},
	"social": {
		"twitter": "",
		"fbAppID": "",
		"instagram": "",
		"github": "Recrea-t"
	}
}
